Workbook

Sheet Sheet1
A1: Order ID | B1: Date | C1: Product | D1: Region | E1: Quantity | F1: Unit Price | G1: Unit Cost | H1: Total sales | I1: Total Cost | J1: Profit | K1: Column1
A2: 1001 | B2: 46025 | C2: Laptop | D2: East | E2: 2 | F2: 50000 | G2: 42000 | H2: =E2*F2 -> 100000 | I2: =E2*G2 -> 84000 | J2: =H2-I2 -> 16000 | K2: =COUNTIF(A:A,A2) -> 1
A3: 1009 | B3: 46064 | C3: Laptop | D3: South | E3: 2 | F3: 50000 | G3: 42000 | H3: =E3*F3 -> 100000 | I3: =E3*G3 -> 84000 | J3: =H3-I3 -> 16000 | K3: =COUNTIF(A:A,A3) -> 1
A4: 1005 | B4: 46037 | C4: Laptop | D4: North | E4: 1 | F4: 50000 | G4: 42000 | H4: =E4*F4 -> 50000 | I4: =E4*G4 -> 42000 | J4: =H4-I4 -> 8000 | K4: =COUNTIF(A:A,A4) -> 1
A5: 1007 | B5: 46055 | C5: Monitor | D5: West | E5: 3 | F5: 12000 | G5: 9500 | H5: =E5*F5 -> 36000 | I5: =E5*G5 -> 28500 | J5: =H5-I5 -> 7500 | K5: =COUNTIF(A:A,A5) -> 1
A6: 1004 | B6: 46034 | C6: Monitor | D6: South | E6: 2 | F6: 12000 | G6: 9500 | H6: =E6*F6 -> 24000 | I6: =E6*G6 -> 19000 | J6: =H6-I6 -> 5000 | K6: =COUNTIF(A:A,A6) -> 1
A7: 1011 | B7: 46073 | C7: Monitor | D7: East | E7: 1 | F7: 12000 | G7: 9500 | H7: =E7*F7 -> 12000 | I7: =E7*G7 -> 9500 | J7: =H7-I7 -> 2500 | K7: =COUNTIF(A:A,A7) -> 1
A8: 1012 | B8: 46078 | C8: Keyboard | D8: West | E8: 6 | F8: 1500 | G8: 900 | H8: =E8*F8 -> 9000 | I8: =E8*G8 -> 5400 | J8: =H8-I8 -> 3600 | K8: =COUNTIF(A:A,A8) -> 1
A9: 1006 | B9: 46040 | C9: Mouse | D9: East | E9: 10 | F9: 800 | G9: 450 | H9: =E9*F9 -> 8000 | I9: =E9*G9 -> 4500 | J9: =H9-I9 -> 3500 | K9: =COUNTIF(A:A,A9) -> 1
A10: 1010 | B10: 46068 | C10: Mouse | D10: North | E10: 8 | F10: 800 | G10: 450 | H10: =E10*F10 -> 6400 | I10: =E10*G10 -> 3600 | J10: =H10-I10 -> 2800 | K10: =COUNTIF(A:A,A10) -> 1
A11: 1008 | B11: 46059 | C11: Keyboard | D11: North | E11: 4 | F11: 1500 | G11: 900 | H11: =E11*F11 -> 6000 | I11: =E11*G11 -> 3600 | J11: =H11-I11 -> 2400 | K11: =COUNTIF(A:A,A11) -> 1
A12: 1003 | B12: 46030 | C12: Keyboard | D12: East | E12: 3 | F12: 1500 | G12: 900 | H12: =E12*F12 -> 4500 | I12: =E12*G12 -> 2700 | J12: =H12-I12 -> 1800 | K12: =COUNTIF(A:A,A12) -> 1
A13: 1002 | B13: 46027 | C13: Mouse | D13: West | E13: 5 | F13: 800 | G13: 450 | H13: =E13*F13 -> 4000 | I13: =E13*G13 -> 2250 | J13: =H13-I13 -> 1750 | K13: =COUNTIF(A:A,A13) -> 1
G14: Grand Total | H14: =SUM(H13:H13) -> 4000 | I14: =SUM(I13:I13) -> 2250 | J14: =H14-I14 -> 1750 | K14: =COUNTIF(A:A,A14) -> 0

Sheet Product Analysis
A1: Product | B1: Total Sales
A2: Laptop | B2: =SUMIF(Sheet1!$C$2:$C$13,A2,Sheet1!$H$2:$H$13) -> 250000
A3: mouse | B3: =SUMIF(Sheet1!$C$2:$C$13,A3,Sheet1!$H$2:$H$13) -> 18400
A4: Keyboard | B4: =SUMIF(Sheet1!$C$2:$C$13,A4,Sheet1!$H$2:$H$13) -> 19500
A5: Monitor | B5: =SUMIF(Sheet1!$C$2:$C$13,A5,Sheet1!$H$2:$H$13) -> 72000

Sheet Dashboard
A1: RETAIL SALES DASHBOARD
A3: Total Revenue | B3: =SUM(Sheet1!H2:H13) -> 359900 | D3: Total Profit | E3: =SUM(Sheet1!J2:J13) -> 70850 | G3: Gross Profit Margin | H3: =E3/B3 -> 0.19686024 | J3: Total Transactions | K3: =COUNTA(Sheet1!A2:A13) -> 12
A6: Key Business Findings
A7: 1. Laptops generated the highest product revenue at 250000
A8: 2. The East region led sales with 1,24,000
A9: 3. Gross profit margin was 19.69% across all transactions.
